MANIFEST.in
README.md
setup.py
siml/__init__.py
siml/detect_peaks.py
siml/evaluators.py
siml/load_data.py
siml/logistic_regression.py
siml/naive_bayes.py
siml/perceptron.py
siml/signal_analysis_utils.py
siml/sk_utils.py
siml.egg-info/PKG-INFO
siml.egg-info/SOURCES.txt
siml.egg-info/dependency_links.txt
siml.egg-info/not-zip-safe
siml.egg-info/requires.txt
siml.egg-info/top_level.txt