Metadata-Version: 1.0
Name: siml
Version: 0.3.1
Summary: Machine Learning algorithms implemented from scratch
Home-page: https://github.com/taspinar/siml
Author: Ahmet Taspinar
Author-email: taspinar@gmail.com
License: MIT
Platform: UNKNOWN
